zipcode_features/__init__.py
zipcode_features-0.0.2.dist-info/licenses/LICENSE
zipcode_features-0.0.2.dist-info/METADATA
zipcode_features-0.0.2.dist-info/WHEEL
zipcode_features-0.0.2.dist-info/top_level.txt
zipcode_features-0.0.2.dist-info/RECORD
